easyeda2kicad/__init__.py
easyeda2kicad/__main__.py
easyeda2kicad/helpers.py
easyeda2kicad/easyeda/__init__.py
easyeda2kicad/easyeda/easyeda_api.py
easyeda2kicad/easyeda/easyeda_importer.py
easyeda2kicad/easyeda/parameters_easyeda.py
easyeda2kicad/easyeda/svg_path_parser.py
easyeda2kicad/kicad/__init__.py
easyeda2kicad/kicad/export_kicad_3d_model.py
easyeda2kicad/kicad/export_kicad_footprint.py
easyeda2kicad/kicad/export_kicad_symbol.py
easyeda2kicad/kicad/parameters_kicad_footprint.py
easyeda2kicad/kicad/parameters_kicad_symbol.py
easyeda2kicad-0.8.0.dist-info/LICENSE
easyeda2kicad-0.8.0.dist-info/METADATA
easyeda2kicad-0.8.0.dist-info/WHEEL
easyeda2kicad-0.8.0.dist-info/entry_points.txt
easyeda2kicad-0.8.0.dist-info/top_level.txt
easyeda2kicad-0.8.0.dist-info/RECORD
